Workbook
Name Slicer_Month: #N/A
Name Slicer_Month1: #N/A

Sheet Pivot tables
A1: Anualls
A3: Sum of Amount | B3: Column Labels
A4: Row Labels | B4: January | C4: February | D4: Grand Total
A5: Rent | B5: 850 | C5: 850 | D5: 1700
A6: Grand Total | B6: 850 | C6: 850 | D6: 1700
A8: Sum of Amount | B8: Column Labels
A9: Row Labels | B9: January | C9: February | D9: Grand Total
A10: Transport | B10: 55 | C10: 55 | D10: 110
A11: Grand Total | B11: 55 | C11: 55 | D11: 110
A13: Sum of Amount | B13: Column Labels
A14: Row Labels | B14: January | C14: February | D14: Grand Total
A15: Utilities | B15: 140 | C15: 105 | D15: 245
A16: Grand Total | B16: 140 | C16: 105 | D16: 245
A18: Sum of Amount | B18: Column Labels
A19: Row Labels | B19: January | C19: February | D19: Grand Total
A20: Groceries | B20: 449 | C20: 305 | D20: 754
A21: Grand Total | B21: 449 | C21: 305 | D21: 754
A23: Sum of Amount | B23: Column Labels
A24: Row Labels | B24: January | C24: February | D24: Grand Total
A25: Leisure | B25: 562 | C25: 194 | D25: 756
A26: Grand Total | B26: 562 | C26: 194 | D26: 756
A28: Sum of Amount | B28: Column Labels
A29: Row Labels | B29: January | C29: February | D29: Grand Total
A30: Other | B30: 249 | C30: 18 | D30: 267
A31: Grand Total | B31: 249 | C31: 18 | D31: 267
A33: Budget
A35: total | B35: =GETPIVOTDATA("Budget",$A$36,"Category","Rent") -> 8500
A36: Sum of Budget | B36: Column Labels
A37: Row Labels | B37: February | C37: March | D37: April | E37: May | F37: June | G37: August | H37: September | I37: October | J37: November | K37: December | L37: Grand Total
A38: Rent | B38: 850 | C38: 850 | D38: 850 | E38: 850 | F38: 850 | G38: 850 | H38: 850 | I38: 850 | J38: 850 | K38: 850 | L38: 8500
A39: Grand Total | B39: 850 | C39: 850 | D39: 850 | E39: 850 | F39: 850 | G39: 850 | H39: 850 | I39: 850 | J39: 850 | K39: 850 | L39: 8500
A41: total | B41: =GETPIVOTDATA("Budget",$A$42,"Category","Transport") -> 750
A42: Sum of Budget | B42: Column Labels
A43: Row Labels | B43: February | C43: March | D43: April | E43: May | F43: June | G43: August | H43: September | I43: October | J43: November | K43: December | L43: Grand Total
A44: Transport | B44: 75 | C44: 75 | D44: 75 | E44: 75 | F44: 75 | G44: 75 | H44: 75 | I44: 75 | J44: 75 | K44: 75 | L44: 750
A45: Grand Total | B45: 75 | C45: 75 | D45: 75 | E45: 75 | F45: 75 | G45: 75 | H45: 75 | I45: 75 | J45: 75 | K45: 75 | L45: 750
A47: total | B47: =GETPIVOTDATA("Budget",$A$48,"Category","Groceries") -> 5500
A48: Sum of Budget | B48: Column Labels
A49: Row Labels | B49: February | C49: March | D49: April | E49: May | F49: June | G49: August | H49: September | I49: October | J49: November | K49: December | L49: Grand Total
A50: Groceries | B50: 550 | C50: 550 | D50: 550 | E50: 550 | F50: 550 | G50: 550 | H50: 550 | I50: 550 | J50: 550 | K50: 550 | L50: 5500
A51: Grand Total | B51: 550 | C51: 550 | D51: 550 | E51: 550 | F51: 550 | G51: 550 | H51: 550 | I51: 550 | J51: 550 | K51: 550 | L51: 5500
A53: total | B53: =GETPIVOTDATA("Budget",$A$54,"Category","Leisure") -> 4000
A54: Sum of Budget | B54: Column Labels
A55: Row Labels | B55: February | C55: March | D55: April | E55: May | F55: June | G55: August | H55: September | I55: October | J55: November | K55: December | L55: Grand Total
A56: Leisure | B56: 400 | C56: 400 | D56: 400 | E56: 400 | F56: 400 | G56: 400 | H56: 400 | I56: 400 | J56: 400 | K56: 400 | L56: 4000
A57: Grand Total | B57: 400 | C57: 400 | D57: 400 | E57: 400 | F57: 400 | G57: 400 | H57: 400 | I57: 400 | J57: 400 | K57: 400 | L57: 4000
A59: total | B59: =GETPIVOTDATA("Budget",$A$60,"Category","Utilities") -> 2000
A60: Sum of Budget | B60: Column Labels
A61: Row Labels | B61: February | C61: March | D61: April | E61: May | F61: June | G61: August | H61: September | I61: October | J61: November | K61: December | L61: Grand Total
A62: Utilities | B62: 200 | C62: 200 | D62: 200 | E62: 200 | F62: 200 | G62: 200 | H62: 200 | I62: 200 | J62: 200 | K62: 200 | L62: 2000
A63: Grand Total | B63: 200 | C63: 200 | D63: 200 | E63: 200 | F63: 200 | G63: 200 | H63: 200 | I63: 200 | J63: 200 | K63: 200 | L63: 2000
A65: total | B65: =GETPIVOTDATA("Budget",$A$66,"Category","Other") -> 3000
A66: Sum of Budget | B66: Column Labels
A67: Row Labels | B67: February | C67: March | D67: April | E67: May | F67: June | G67: August | H67: September | I67: October | J67: November | K67: December | L67: Grand Total
A68: Other | B68: 300 | C68: 300 | D68: 300 | E68: 300 | F68: 300 | G68: 300 | H68: 300 | I68: 300 | J68: 300 | K68: 300 | L68: 3000
A69: Grand Total | B69: 300 | C69: 300 | D69: 300 | E69: 300 | F69: 300 | G69: 300 | H69: 300 | I69: 300 | J69: 300 | K69: 300 | L69: 3000
A71: Charts
A73: Income / Expense | B73: Expense
A75: Sum of Amount | B75: Column Labels
A76: Row Labels | B76: January | C76: February | D76: Grand Total
A77: Groceries | B77: 449 | C77: 305 | D77: 754
A78: Leisure | B78: 562 | C78: 194 | D78: 756
A79: Other | B79: 249 | C79: 18 | D79: 267
A80: Rent | B80: 850 | C80: 850 | D80: 1700
A81: Transport | B81: 55 | C81: 55 | D81: 110
A82: Utilities | B82: 140 | C82: 105 | D82: 245
A83: Grand Total | B83: 2305 | C83: 1527 | D83: 3832
A85: =A77 -> Groceries | B85: =GETPIVOTDATA("Amount",$A$75,"Category","Groceries") -> 754
A86: =A78 -> Leisure | B86: =GETPIVOTDATA("Amount",$A$75,"Category","Leisure") -> 756
A87: =A79 -> Other | B87: =GETPIVOTDATA("Amount",$A$75,"Category","Other") -> 267
A88: =A80 -> Rent | B88: =GETPIVOTDATA("Amount",$A$75,"Category","Rent") -> 1700
A89: =A81 -> Transport | B89: =GETPIVOTDATA("Amount",$A$75,"Category","Transport") -> 110
A90: =A82 -> Utilities | B90: =GETPIVOTDATA("Amount",$A$75,"Category","Utilities") -> 245
A94: Sum of Amount | B94: Column Labels
A95: Row Labels | B95: January | C95: February | D95: Grand Total
A96: Expense | B96: 2305 | C96: 1527 | D96: 3832
A97: Income | B97: 3642 | C97: 3533 | D97: 7175
A98: Grand Total | B98: 5947 | C98: 5060 | D98: 11007
A100: =A96 -> Expense | B100: =GETPIVOTDATA("Amount",$A$94,"Income / Expense","Expense") -> 3832
A101: =A97 -> Income | B101: =GETPIVOTDATA("Amount",$A$94,"Income / Expense","Income") -> 7175
A104: Starting Cash Balance | B104: =Dashboard!B11 -> 3000
A105: Changing Cash | B105: =B101-B100 -> 3343
A106: Ending Cash Balance | B106: =B104+B105 -> 6343
A108: Actual Expense | B108: =GETPIVOTDATA("Amount",$A$94,"Income / Expense","Expense") -> 3832
A109: Actual Income | B109: =GETPIVOTDATA("Amount",$A$94,"Income / Expense","Income") -> 7175
A111: Sum of Budget | B111: Column Labels
A112: Row Labels | B112: February | C112: March | D112: April | E112: May | F112: June | G112: August | H112: September | I112: October | J112: November | K112: December | L112: Grand Total
A113: Expense | B113: 2375 | C113: 2375 | D113: 2375 | E113: 2375 | F113: 2375 | G113: 2375 | H113: 2375 | I113: 2375 | J113: 2375 | K113: 2375 | L113: 23750
A114: Income | B114: 2800 | C114: 2800 | D114: 2800 | E114: 2800 | F114: 2800 | G114: 2800 | H114: 2800 | I114: 2800 | J114: 2800 | K114: 2800 | L114: 28000
A115: Grand Total | B115: 5175 | C115: 5175 | D115: 5175 | E115: 5175 | F115: 5175 | G115: 5175 | H115: 5175 | I115: 5175 | J115: 5175 | K115: 5175 | L115: 51750
A117: Planed Expense | B117: =GETPIVOTDATA("Budget",$A$111,"Income/Expense","Expense") -> 23750
A118: Planed Income | B118: =GETPIVOTDATA("Budget",$A$111,"Income/Expense","Income") -> 28000

Sheet Actuals
B2: Actual Income & Expenses 2022
B4: Date | C4: Month | D4: Category | E4: Description | F4: Income / Expense | G4: Amount | J4: Category | K4: Income/Expense
B5: 44562 | C5: =TEXT(Actuals!$B5,"MMMM") -> January | D5: Rent | E5: Apartment split with friend | F5: =_xlfn.XLOOKUP(Actuals!$D5,$J$5:$J$13,$K$5:$K$13) -> Expense | G5: 850 | J5: Rent | K5: Expense
B6: 44562 | C6: =TEXT(Actuals!$B6,"MMMM") -> January | D6: Utilities | E6: Higher month than usual | F6: =_xlfn.XLOOKUP(Actuals!$D6,$J$5:$J$13,$K$5:$K$13) -> Expense | G6: 140 | J6: Utilities | K6: Expense
B7: 44562 | C7: =TEXT(Actuals!$B7,"MMMM") -> January | D7: Transport | E7: Metro card | F7: =_xlfn.XLOOKUP(Actuals!$D7,$J$5:$J$13,$K$5:$K$13) -> Expense | G7: 55 | J7: Transport | K7: Expense
B8: 44569 | C8: =TEXT(Actuals!$B8,"MMMM") -> January | D8: Groceries | E8: Walmart shopping | F8: =_xlfn.XLOOKUP(Actuals!$D8,$J$5:$J$13,$K$5:$K$13) -> Expense | G8: 449 | J8: Groceries | K8: Expense
B9: 44572 | C9: =TEXT(Actuals!$B9,"MMMM") -> January | D9: Leisure | E9: Hotel in NYC | F9: =_xlfn.XLOOKUP(Actuals!$D9,$J$5:$J$13,$K$5:$K$13) -> Expense | G9: 245 | J9: Leisure | K9: Expense
B10: 44573 | C10: =TEXT(Actuals!$B10,"MMMM") -> January | D10: Leisure | E10: Dinner with friends (invited my partner) | F10: =_xlfn.XLOOKUP(Actuals!$D10,$J$5:$J$13,$K$5:$K$13) -> Expense | G10: 168 | J10: Other | K10: Expense
B11: 44573 | C11: =TEXT(Actuals!$B11,"MMMM") -> January | D11: Leisure | E11: Drake concert | F11: =_xlfn.XLOOKUP(Actuals!$D11,$J$5:$J$13,$K$5:$K$13) -> Expense | G11: 149 | J11: Bonus | K11: Income
B12: 44575 | C12: =TEXT(Actuals!$B12,"MMMM") -> January | D12: Other | E12: Bought new clothes | F12: =_xlfn.XLOOKUP(Actuals!$D12,$J$5:$J$13,$K$5:$K$13) -> Expense | G12: 249 | J12: Base Salary | K12: Income
B13: 44592 | C13: =TEXT(Actuals!$B13,"MMMM") -> January | D13: Bonus | E13: Commissions from each sale | F13: =_xlfn.XLOOKUP(Actuals!$D13,$J$5:$J$13,$K$5:$K$13) -> Income | G13: 458 | J13: Side Hustle | K13: Income
B14: 44592 | C14: =TEXT(Actuals!$B14,"MMMM") -> January | D14: Base Salary | E14: 9-5 job | F14: =_xlfn.XLOOKUP(Actuals!$D14,$J$5:$J$13,$K$5:$K$13) -> Income | G14: 3000
B15: 44592 | C15: =TEXT(Actuals!$B15,"MMMM") -> January | D15: Side Hustle | E15: Startup idea $ | F15: =_xlfn.XLOOKUP(Actuals!$D15,$J$5:$J$13,$K$5:$K$13) -> Income | G15: 184
B16: 44593 | C16: =TEXT(Actuals!$B16,"MMMM") -> February | D16: Rent | E16: Apartment split with friend | F16: =_xlfn.XLOOKUP(Actuals!$D16,$J$5:$J$13,$K$5:$K$13) -> Expense | G16: 850
B17: 44593 | C17: =TEXT(Actuals!$B17,"MMMM") -> February | D17: Utilities | E17: Average month | F17: =_xlfn.XLOOKUP(Actuals!$D17,$J$5:$J$13,$K$5:$K$13) -> Expense | G17: 105
B18: 44593 | C18: =TEXT(Actuals!$B18,"MMMM") -> February | D18: Transport | E18: Metro card | F18: =_xlfn.XLOOKUP(Actuals!$D18,$J$5:$J$13,$K$5:$K$13) -> Expense | G18: 55
B19: 44600 | C19: =TEXT(Actuals!$B19,"MMMM") -> February | D19: Groceries | E19: Walmart shopping | F19: =_xlfn.XLOOKUP(Actuals!$D19,$J$5:$J$13,$K$5:$K$13) -> Expense | G19: 305
B20: 44603 | C20: =TEXT(Actuals!$B20,"MMMM") -> February | D20: Leisure | E20: Drinks out | F20: =_xlfn.XLOOKUP(Actuals!$D20,$J$5:$J$13,$K$5:$K$13) -> Expense | G20: 28
B21: 44604 | C21: =TEXT(Actuals!$B21,"MMMM") -> February | D21: Leisure | E21: Date night | F21: =_xlfn.XLOOKUP(Actuals!$D21,$J$5:$J$13,$K$5:$K$13) -> Expense | G21: 99
B22: 44604 | C22: =TEXT(Actuals!$B22,"MMMM") -> February | D22: Leisure | E22: Tennis x2 | F22: =_xlfn.XLOOKUP(Actuals!$D22,$J$5:$J$13,$K$5:$K$13) -> Expense | G22: 67
B23: 44606 | C23: =TEXT(Actuals!$B23,"MMMM") -> February | D23: Other | E23: Snacks | F23: =_xlfn.XLOOKUP(Actuals!$D23,$J$5:$J$13,$K$5:$K$13) -> Expense | G23: 18
B24: 44620 | C24: =TEXT(Actuals!$B24,"MMMM") -> February | D24: Bonus | E24: Commissions from each sale | F24: =_xlfn.XLOOKUP(Actuals!$D24,$J$5:$J$13,$K$5:$K$13) -> Income | G24: 305
B25: 44620 | C25: =TEXT(Actuals!$B25,"MMMM") -> February | D25: Base Salary | E25: 9-5 job | F25: =_xlfn.XLOOKUP(Actuals!$D25,$J$5:$J$13,$K$5:$K$13) -> Income | G25: 3000
... B60: 44710 | C60: =TEXT(Actuals!$B60,"MMMM") -> May | D60: Side Hustle | E60: Lemonade | F60: =_xlfn.XLOOKUP(Actuals!$D60,$J$5:$J$13,$K$5:$K$13) -> Income | G60: 1000

Sheet Dashboard
A1: Personal Finance Dashboard
B4: Rent | E4: Transport | H4: Grocery | K4: Utilities | N4: Leisure | Q4: Others
B5: =GETPIVOTDATA("Amount",'Pivot tables'!$A$3,"Category","Rent") -> 1700 | E5: =GETPIVOTDATA("Amount",'Pivot tables'!$A$8,"Category","Transport") -> 110 | H5: =GETPIVOTDATA("Amount",'Pivot tables'!$A$18,"Category","Groceries") -> 754 | K5: =GETPIVOTDATA("Amount",'Pivot tables'!$A$13,"Category","Utilities") -> 245 | N5: =GETPIVOTDATA("Amount",'Pivot tables'!$A$23,"Category","Leisure") -> 756 | Q5: =GETPIVOTDATA("Amount",'Pivot tables'!$A$28,"Category","Other") -> 267
B9: Starting Cash Balance
B11: 3000

Sheet Budget
B2: Budget Income & Expenses 2022
B4: Month | C4: Category | D4: Budget | E4: Income/Expense
B5: January | C5: Rent | D5: 850 | E5: =_xlfn.XLOOKUP(Budget!$C5,Actuals!$J$5:$J$13,Actuals!$K$5:$K$13) -> Expense
B6: January | C6: Utilities | D6: 200 | E6: =_xlfn.XLOOKUP(Budget!$C6,Actuals!$J$5:$J$13,Actuals!$K$5:$K$13) -> Expense
B7: January | C7: Transport | D7: 75 | E7: =_xlfn.XLOOKUP(Budget!$C7,Actuals!$J$5:$J$13,Actuals!$K$5:$K$13) -> Expense
B8: January | C8: Groceries | D8: 550 | E8: =_xlfn.XLOOKUP(Budget!$C8,Actuals!$J$5:$J$13,Actuals!$K$5:$K$13) -> Expense
B9: January | C9: Leisure | D9: 400 | E9: =_xlfn.XLOOKUP(Budget!$C9,Actuals!$J$5:$J$13,Actuals!$K$5:$K$13) -> Expense
B10: January | C10: Other | D10: 300 | E10: =_xlfn.XLOOKUP(Budget!$C10,Actuals!$J$5:$J$13,Actuals!$K$5:$K$13) -> Expense
B11: January | C11: Bonus | D11: 2200 | E11: =_xlfn.XLOOKUP(Budget!$C11,Actuals!$J$5:$J$13,Actuals!$K$5:$K$13) -> Income
B12: January | C12: Base Salary | D12: 500 | E12: =_xlfn.XLOOKUP(Budget!$C12,Actuals!$J$5:$J$13,Actuals!$K$5:$K$13) -> Income
B13: January | C13: Side Hustle | D13: 100 | E13: =_xlfn.XLOOKUP(Budget!$C13,Actuals!$J$5:$J$13,Actuals!$K$5:$K$13) -> Income
B14: February | C14: Rent | D14: 850 | E14: =_xlfn.XLOOKUP(Budget!$C14,Actuals!$J$5:$J$13,Actuals!$K$5:$K$13) -> Expense
B15: February | C15: Utilities | D15: 200 | E15: =_xlfn.XLOOKUP(Budget!$C15,Actuals!$J$5:$J$13,Actuals!$K$5:$K$13) -> Expense
B16: February | C16: Transport | D16: 75 | E16: =_xlfn.XLOOKUP(Budget!$C16,Actuals!$J$5:$J$13,Actuals!$K$5:$K$13) -> Expense
... B112: December | C112: Side Hustle | D112: 100 | E112: =_xlfn.XLOOKUP(Budget!$C112,Actuals!$J$5:$J$13,Actuals!$K$5:$K$13) -> Income
